README.md
setup.py
bitvavo/BitvavoClient.py
bitvavo/BitvavoExceptions.py
bitvavo/Pair.py
bitvavo/Timer.py
bitvavo/__init__.py
bitvavo/enums.py
bitvavo_aio.egg-info/PKG-INFO
bitvavo_aio.egg-info/SOURCES.txt
bitvavo_aio.egg-info/dependency_links.txt
bitvavo_aio.egg-info/requires.txt
bitvavo_aio.egg-info/top_level.txt