Metadata-Version: 2.1
Name: bitvavo-aio
Version: 1.0.1
Summary: Bitvavo asynchronous Python client
Home-page: https://github.com/cyberjunky/bitvavo-aio
Author: @cyberjunky
Author-email: ron@cyberjunky.nl
License: UNKNOWN
Platform: UNKNOWN
Classifier: Development Status :: 4 - Beta
Classifier: Framework :: AsyncIO
Classifier: Intended Audience :: Developers
Classifier: Programming Language :: Python :: 3
Classifier: Programming Language :: Python :: 3.6
Classifier: Programming Language :: Python :: 3.7
Classifier: License :: OSI Approved :: MIT License
Classifier: Operating System :: OS Independent
Classifier: Topic :: Software Development :: Libraries
Classifier: Topic :: Software Development :: Libraries :: Python Modules
Classifier: Typing :: Typed
Requires-Python: >=3.6
